mgoelAuto/__init__.py
mgoelAuto/__main__.py
mgoelAuto/appLogger.py
mgoelAuto/classificationModels.py
mgoelAuto/data_loader.py
mgoelAuto/file_methods.py
mgoelAuto/preProcess.py
mgoelAuto/predict.py
mgoelAuto/regressionModels.py
mgoelAuto/visualization.py
mgoelAuto/logs/RegressionTrainingLogs.txt
mgoelAuto/logs/classificationTrainingLogs.txt
mgoelAuto/logs/dataLoadLogs.txt
mgoelAuto/logs/dataPreprocessingLogs.txt
mgoelAuto/logs/dataVisualizationLogs.txt
mgoelAuto/logs/fileOperationLogs.txt
mgoelAuto/logs/predictionLogs.txt
mgoelAuto/logs/test.txt
mgoelAuto/models/RandomForest.sav
mgoelAuto/static/assets/demo/chart-area-demo.js
mgoelAuto/static/assets/demo/chart-bar-demo.js
mgoelAuto/static/assets/demo/chart-pie-demo.js
mgoelAuto/static/assets/demo/datatables-demo.js
mgoelAuto/static/assets/img/error-404-monochrome.svg
mgoelAuto/static/css/styles.css
mgoelAuto/static/graphs/correlation.png
mgoelAuto/static/graphs/test.jpg
mgoelAuto/static/js/scripts.js
mgoelAuto/static/scripts/build-assets.js
mgoelAuto/static/scripts/build-pug.js
mgoelAuto/static/scripts/build-scripts.js
mgoelAuto/static/scripts/build-scss.js
mgoelAuto/static/scripts/clean.js
mgoelAuto/static/scripts/render-assets.js
mgoelAuto/static/scripts/render-pug.js
mgoelAuto/static/scripts/render-scripts.js
mgoelAuto/static/scripts/render-scss.js
mgoelAuto/static/scripts/sb-watch.js
mgoelAuto/static/scripts/start-debug.js
mgoelAuto/static/scripts/start.js
mgoelAuto/templates/401.html
mgoelAuto/templates/404.html
mgoelAuto/templates/500.html
mgoelAuto/templates/charts.html
mgoelAuto/templates/index.html
mgoelAuto/templates/layout-sidenav-light.html
mgoelAuto/templates/layout-static.html
mgoelAuto/templates/login.html
mgoelAuto/templates/model_report_classification.html
mgoelAuto/templates/model_report_regression.html
mgoelAuto/templates/password.html
mgoelAuto/templates/prediction.html
mgoelAuto/templates/prediction_results.html
mgoelAuto/templates/register.html
mgoelAuto/templates/tables.html
mgoelAuto-1.1.1.dist-info/METADATA
mgoelAuto-1.1.1.dist-info/WHEEL
mgoelAuto-1.1.1.dist-info/entry_points.txt
mgoelAuto-1.1.1.dist-info/top_level.txt
mgoelAuto-1.1.1.dist-info/RECORD
